<?xml version="1.0" encoding="UTF-8" ?>
<!DOCTYPE mapper PUBLIC "-//mybatis.org//DTD Mapper 3.0//EN" "http://mybatis.org/dtd/mybatis-3-mapper.dtd">
<mapper namespace="cn.goodym.java.modules.oa.dao.OaOutDao">
    
	<sql id="oaOutColumns">
		a.id AS "id",
		a.true_name AS "trueName",
		a.office_id AS "office.id",
		a.out_type AS "outType",
		a.out_date AS "outDate",
		a.start_time AS "startTime",
		a.end_time AS "endTime",
		a.hour_total AS "hourTotal",
		a.out_status AS "outStatus",
		a.reason AS "reason",
		a.create_by AS "createBy.id",
		a.create_date AS "createDate",
		a.update_by AS "updateBy.id",
		a.update_date AS "updateDate",
		a.remarks AS "remarks",
		a.del_flag AS "delFlag",
		o3.name AS "office.name"
	</sql>
	
	<sql id="oaOutJoins">
		LEFT JOIN sys_office o3 ON o3.id = a.office_id
	</sql>
    
	<select id="get" resultType="OaOut">
		SELECT 
			<include refid="oaOutColumns"/>
		FROM oa_out a
		<include refid="oaOutJoins"/>
		WHERE a.id = #{id}
	</select>
	
	<select id="findList" resultType="OaOut">
		SELECT 
			<include refid="oaOutColumns"/>
		FROM oa_out a
		<include refid="oaOutJoins"/>
		<where>
			a.del_flag = #{DEL_FLAG_NORMAL}
			<if test="trueName != null and trueName != ''">
				AND a.true_name = #{trueName}
			</if>
			<if test="office != null and office.id != null and office.id != ''">
				AND a.office_id = #{office.id}
			</if>
			<if test="outStatus != null and outStatus != ''">
				AND a.out_status = #{outStatus}
			</if>
		</where>
		<choose>
			<when test="page !=null and page.orderBy != null and page.orderBy != ''">
				ORDER BY ${page.orderBy}
			</when>
			<otherwise>
				ORDER BY a.update_date DESC
			</otherwise>
		</choose>
	</select>
	
	<select id="findAllList" resultType="OaOut">
		SELECT 
			<include refid="oaOutColumns"/>
		FROM oa_out a
		<include refid="oaOutJoins"/>
		<where>
			a.del_flag = #{DEL_FLAG_NORMAL}
		</where>		
		<choose>
			<when test="page !=null and page.orderBy != null and page.orderBy != ''">
				ORDER BY ${page.orderBy}
			</when>
			<otherwise>
				ORDER BY a.update_date DESC
			</otherwise>
		</choose>
	</select>
	
	<insert id="insert">
		INSERT INTO oa_out(
			id,
			true_name,
			office_id,
			out_type,
			out_date,
			start_time,
			end_time,
			hour_total,
			out_status,
			reason,
			create_by,
			create_date,
			update_by,
			update_date,
			remarks,
			del_flag
		) VALUES (
			#{id},
			#{trueName},
			#{office.id},
			#{outType},
			#{outDate},
			#{startTime},
			#{endTime},
			#{hourTotal},
			#{outStatus},
			#{reason},
			#{createBy.id},
			#{createDate},
			#{updateBy.id},
			#{updateDate},
			#{remarks},
			#{delFlag}
		)
	</insert>
	
	<update id="update">
		UPDATE oa_out SET 	
			true_name = #{trueName},
			office_id = #{office.id},
			out_type = #{outType},
			out_date = #{outDate},
			start_time = #{startTime},
			end_time = #{endTime},
			hour_total = #{hourTotal},
			out_status = #{outStatus},
			reason = #{reason},
			update_by = #{updateBy.id},
			update_date = #{updateDate},
			remarks = #{remarks}
		WHERE id = #{id}
	</update>
	
	<update id="delete">
		UPDATE oa_out SET 
			del_flag = #{DEL_FLAG_DELETE}
		WHERE id = #{id}
	</update>
	
</mapper>